{
  "entityType" : "DEVICE",
  "entity" : {
    "additionalInfo" : {
      "gateway" : false,
      "overwriteActivityTime" : false,
      "description" : ""
    },
    "customerId" : {
      "entityType" : "CUSTOMER",
      "id" : "13814000-1dd2-11b2-8080-808080808080"
    },
    "deviceData" : {
      "configuration" : {
        "type" : "DEFAULT"
      },
      "transportConfiguration" : {
        "type" : "DEFAULT"
      }
    },
    "deviceProfileId" : {
      "entityType" : "DEVICE_PROFILE",
      "id" : "0cc0f270-3576-11f0-a851-d98fa5765a83"
    },
    "externalId" : null,
    "firmwareId" : null,
    "id" : {
      "entityType" : "DEVICE",
      "id" : "315033a0-3579-11f0-a851-d98fa5765a83"
    },
    "label" : "turbidez_peñafiel",
    "name" : "turbidez_peñafiel",
    "ownerId" : null,
    "softwareId" : null,
    "type" : "turbidez"
  },
  "credentials" : {
    "credentialsId" : "vpm1sfq7oypdrscidheq",
    "credentialsType" : "ACCESS_TOKEN",
    "credentialsValue" : null
  },
  "relations" : [ ],
  "attributes" : {
    "SERVER_SCOPE" : [ {
      "booleanValue" : false,
      "doubleValue" : null,
      "jsonValue" : null,
      "key" : "active",
      "lastUpdateTs" : 1747745508397,
      "longValue" : null,
      "strValue" : null
    } ],
    "SHARED_SCOPE" : [ ]
  },
  "calculatedFields" : [ ]
}